README.rst
setup.py
pymysqlslave/__init__.py
pymysqlslave/dbutils.py
pymysqlslave.egg-info/PKG-INFO
pymysqlslave.egg-info/SOURCES.txt
pymysqlslave.egg-info/dependency_links.txt
pymysqlslave.egg-info/not-zip-safe
pymysqlslave.egg-info/requires.txt
pymysqlslave.egg-info/top_level.txt