Metadata-Version: 1.0
Name: pymysqlslave
Version: 1.0.8
Summary: Simple Master Slave Load Balancing
Home-page: https://github.com/nashuiliang/pymysqlslave
Author: chuangwang
Author-email: nashuiliang@gmail.com
License: Apache License 2.0
Keywords: mysqldb slave master balancing sqlalchemy
Platform: UNKNOWN
